LICENSE
datasoap/__init__.py
datasoap/data_soap.py
datasoap-1.1.2.dist-info/entry_points.txt
datasoap-1.1.2.dist-info/LICENSE
datasoap-1.1.2.dist-info/WHEEL
datasoap-1.1.2.dist-info/METADATA
datasoap-1.1.2.dist-info/RECORD
