Metadata-Version: 2.1
Name: datasoap
Version: 1.1.2
Summary: Supplementary library for pandas that processes dataframes derived from CSV files.
Home-page: https://github.com/Snake-Fingers/datasoap
License: MIT
Author: Mason Fryberger
Author-email: mason.fryberger@gmail.com
Requires-Python: >=3.9,<4.0
Classifier: License :: OSI Approved :: MIT License
Classifier: Operating System :: OS Independent
Classifier: Programming Language :: Python :: 3
Classifier: Programming Language :: Python :: 3.9
Requires-Dist: pandas
Project-URL: Documentation, https://datasoap.readthedocs.io/en/latest/
Project-URL: Repository, https://github.com/Snake-Fingers/datasoap
